bureau/__init__.py
bureau/_version.py
bureau-0.0.1.dist-info/DESCRIPTION.rst
bureau-0.0.1.dist-info/METADATA
bureau-0.0.1.dist-info/RECORD
bureau-0.0.1.dist-info/WHEEL
bureau-0.0.1.dist-info/metadata.json
bureau-0.0.1.dist-info/top_level.txt
