Metadata-Version: 1.0
Name: bureau
Version: 0.0.1
Summary: Bureau handles the administrative tasks of your projects. Command line interfaces, system environment, settings...
Home-page: UNKNOWN
Author: Romain Dorgueil
Author-email: romain@dorgueil.net
License: Apache License, Version 2.0
Platform: UNKNOWN
